{
	"webElements": [
		{
			"name": "menu_system",
			"byType": "classname",
			"definition": "_12-z",
			"frame": "default",
			"specialInstr": "NA"
	
			
		},
		{
			"name": "admin_panel",
			"byType": "xpath",
			"definition": "//*[text()='Admin Panel']",
			"frame": "default",
			"specialInstr": "NA"
			

		},
		{
			"name": "password_reset",
			"byType": "xpath",
			"definition": "/html/body/div[4]/div/div/div/div/div/div[7]/span/div/div/div/span",
			"frame": "default",
			"specialInstr": "NA"
		},
		{
			"name": "password_reset_input",
			"byType": "id",
			"definition": "__passwordReset_emailInput",
			"frame": "default",
			"specialInstr": "NA"
		}, 
		{
			"name": "reset_button",
			"byType": "classname",
			"definition": "_1tkc undefined",
			"frame": "default",
			"specialInstr": "NA"
		},
		{
			"name": "close",
			"byType": "xpath",
			"definition": ".//*[@class='e1ZR']",
			"frame": "default",
			"specialInstr": "NA"

		},
		{
			"name": "close_cheackAccount",
			"byType": "xpath",
			"definition": "/html/body/div[3]/div/div/div[1]/button",
			"frame": "default",
			"specialInstr": "NA"
		
		},
		{
			"name": "manage_roles",
			"byType": "xpath",
			"definition": "/html/body/div[4]/div/div/div/div/div/div[10]/span/div/div/div/span",
			"frame": "default",
			"specialInstr": "NA",
			"waitToBeVisible": "enter_email_address"
		},
		{
			"name": "check_account",
			"byType": "xpath",
			"definition": "/html/body/div[4]/div/div/div/div/div/div[1]/span/div/div/div/span",
			"frame": "default",
			"specialInstr": "NA",
			"waitToBeVisible": "enter_email_address"
		},
		
		{
			"name": "enter_email_address",
			"byType": "id",
			"definition": "__manageRoles_emailInput",
			"frame": "default",
			"specialInstr": "NA"
		},
		{
			"name": "choose_role",
			"byType": "name",
			"definition": "role",
			"frame": "default",
			"specialInstr":  "enterAfter"
		},
		{
			"name": "role_window",
			"byType": "classname",
			"definition": "_3y07",
			"frame": "default",
			"specialInstr": "NA"
		},
		{
			"name": "grant_role",
			"byType": "xpath",
			"definition": "/html/body/div[3]/div/div/div[2]/button[1]/div/span",
			"frame": "default",
			"specialInstr": "NA",
			"waitForElementToBeEnabled": true,
			"waitForElementToBeInvisible": "role_window"
		},
		{
			"name": "revoke_role",
			"byType": "xpath",
			"definition": "/html/body/div[3]/div/div/div[2]/button[2]",
			"frame": "default",
			"specialInstr": "NA",
			"waitForElementToBeEnabled": true,
			"waitForElementToBeInvisible": "role_window"
		},
		{
			"name": "error_text",
			"byType": "xpath",
			"definition": "/html/body/div[3]/div/div/div[2]/div/div[1]/div[1]",
			"frame": "default",
			"specialInstr": "NA",
			"waitForElementToBeInvisible": "role_window"
		},
		{
			"name": "search_button",
			"byType": "xpath",
			"definition": "//button[contains(@class,'_1Kr1')",
			"frame": "default",
			"specialInstr": "NA"
			
		},
		{
			"name": "search_course",
			"byType": "xpath",
			"definition": ".//*[@class='_3dMU _3Gh- ']",
			"frame": "default",
			"specialInstr": "NA"
			
		},
	
		{
			"name":"copy_course",
            "byType":"xpath",
            "definition":"/html/body/div[3]/div/div/div/div/div/div[2]/span/div/div/div/span",
            "frame":"default",
            "specialInstr":"NA"
		},
		{
			"name":"copy_course_name",
            "byType":"id",
            "definition":"copyCourseName",
            "frame":"default",
            "specialInstr":"NA"
		},
		{
			"name":"save_button",
            "byType":"classname",
            "definition":"_1tkc undefined",
            "frame":"default",
            "specialInstr":"NA"
		},
		{
			"name":"Manage_Instructor",
            "byType":"xpath",
            "definition":"/html/body/div[3]/div/div/div/div/div/div[2]/span/div/div/div/span",
            "frame":"default",
			"specialInstr":"NA",
			"waitToBeVisible":"Instructor_Email"
		},
		{
			"name":"Instructor_Email",
            "byType":"id",
            "definition":"addInstructor",
            "frame":"default",
			"specialInstr":"NA"
			
		},
		{
			"name":"Add_instructor",
            "byType":"classname",
            "definition":"_1tkc _3ASk",
            "frame":"default",
			"specialInstr":"NA",
			"waitToBeVisible":"copy_link"
		},
		{
			"name":"copy_link",
            "byType":"xpath",
            "definition":".//*[@class='_1tkc _6KWa']",
            "frame":"default",
            "specialInstr":"NA"

		},
		{
			"name":"close",
            "byType":"xpath",
            "definition":".//*[@class='e1ZR']",
            "frame":"default",
            "specialInstr":"NA"

		},
		{
			"name":"course_card",
            "byType":"xpath",
            "definition":"//*[@id='container']/div/div[2]/div[1]/div/div/div[3]/div",
            "frame":"default",
			"specialInstr":"NA", 
			"waitToBeVisible": "menu_system"
		
		},
		{
			"name":"refresh",
            "byType":"xpath",
            "definition":"//*[@id='click-to-refresh']/span",
            "frame":"default",
            "specialInstr":"NA"
		},
		{
			"name":"temp_username",
            "byType":"xpath",
            "definition":".//*[@id='identifierId']",
            "frame":"default",
            "specialInstr":"NA"
		},
		{
			"name":"temp_password",
            "byType":"xpath",
            "definition":"//*[@jsname='YPqjbf']",
            "frame":"default",
            "specialInstr":"NA"
		},
		{
			"name":"temp_next",
            "byType":"xpath",
            "definition":"//*[@id='identifierNext']/content/span",
            "frame":"default",
            "specialInstr":"NA"

		},
		{
			"name":"temp_password_next",
            "byType":"xpath",
            "definition":"//*[text()='Next']",
            "frame":"default",
            "specialInstr":"NA"

		},
		{
			"name":"create_access_code",
            "byType":"xpath",
            "definition":".//*[text()='Create Access Code']",
            "frame":"default",
            "specialInstr":"NA"

		},

		{
			"name":"users",
            "byType":"xpath",
            "definition":"//*[@class='_1qpH']",
            "frame":"default",
            "specialInstr":"NA"

		},
		{
			"name":"gmail",
            "byType":"xpath",
            "definition":"//*[@id='yDmH0d']/div[2]/c-wiz/div/div/div[5]/div[2]/c-wiz/div/div[1]/div/div[1]/div[2]/a[2]",
            "frame":"default",
            "specialInstr":"NA"

		},
		{
			"name":"create_course_button",
            "byType":"xpath",
            "definition":"//*[text()='Create Accesscode']",
            "frame":"default",
            "specialInstr":"NA"

		},
		{
			"name":"mail",
            "byType":"xpath",
            "definition":"(//*[text()='Macmillan Learning :: Reset Password'])[2]",
            "frame":"default",
			"specialInstr":"NA"

		},
		{
			"name":"temp_reset_password",
            "byType":"xpath",
            "definition":"//*[@id=':7h']/div/table/tbody/tr/td/center/table[2]/tbody/tr[1]/td/p[2]/a",
            "frame":"default",
            "specialInstr":"NA"

		},
		{
			"name":"login_again",
            "byType":"xpath",
            "definition":"//*[@id='refererLink']",
            "frame":"default",
            "specialInstr":"NA"
		}, 
		{
			"name":"reset_password_email",
            "byType":"id",
            "definition":"update",
            "frame":"default",
            "specialInstr":"NA"
		},
		{
			"name":"back_login",
            "byType":"xpath",
            "definition":"//*[@id='refererLink']",
            "frame":"default",
            "specialInstr":"NA"
		},
	
		{
			"name":"reset_check",
            "byType":"xpath",
            "definition":"(//*[@class='pad'])[1]",
            "frame":"default",
            "specialInstr":"NA"
		},
		{
			"name":"check",
            "byType":"xpath",
            "definition":"//*[@class='_1YVk']",
            "frame":"default",
            "specialInstr":"NA"

		},
		{ 
			"name":"single_use_code",
            "byType":"xpath",
            "definition":"//*[@class='_1qpH']",
            "frame":"default",
            "specialInstr":"NA"

		},
		{ 
			"name":"course_validation",
            "byType":"xpath",
            "definition":"//*[text()='Courses']",
            "frame":"default",
            "specialInstr":"NA"

		}
		



	]
}